byol_pytorch/__init__.py
byol_pytorch/byol_pytorch.py
byol_pytorch/trainer.py
byol_pytorch-0.8.2.dist-info/LICENSE
byol_pytorch-0.8.2.dist-info/METADATA
byol_pytorch-0.8.2.dist-info/WHEEL
byol_pytorch-0.8.2.dist-info/top_level.txt
byol_pytorch-0.8.2.dist-info/RECORD
